catchy/__init__.py
catchy/io.py
catchy/script_base.py
catchy/script_high.py
catchy/script_mid.py
catchy/utils.py
catchy/base/__init__.py
catchy/base/bark_bands.py
catchy/base/base_features.py
catchy/base/hpcp.py
catchy/base/loudness.py
catchy/base/melodia.py
catchy/base/peak_picking.py
catchy/base/roughness.py
catchy/base/sharpness.py
catchy/high/__init__.py
catchy/high/feature_transforms.py
catchy/mid/__init__.py
catchy/mid/pitch_features.py
catchy/mid/rhythm_features.py
tests/base/__init__.py
tests/base/integration_base_test.py
tests/base/test_base.py
catchy_toolbox-0.3.dist-info/LICENSE
catchy_toolbox-0.3.dist-info/METADATA
catchy_toolbox-0.3.dist-info/WHEEL
catchy_toolbox-0.3.dist-info/top_level.txt
catchy_toolbox-0.3.dist-info/zip-safe
catchy_toolbox-0.3.dist-info/RECORD
