Metadata-Version: 2.1
Name: catchy-toolbox
Version: 0.3
Summary: Corpus Analysis Tools for Computational Hook discovery
Home-page: https://github.com/jaburgoyne/catchy
Maintainer: ivan.bobrov
Maintainer-email: id.bobrov@gmail.com
License: MIT
Platform: UNKNOWN
Requires-Python: >=3
Requires-Dist: numpy
Requires-Dist: scipy
Requires-Dist: librosa
Requires-Dist: pandas
